{
  "IE00B5BMR087": {
    "symbol": "SXR8.DE",
    "companyName": "iShares Core S&P 500 UCITS ETF",
    "price": 708.38,
    "originalPrice": 708.38,
    "originalCurrency": "EUR",
    "change": 2.1399999999999864,
    "changesPercentage": 0.30301314000906016,
    "currency": "EUR",
    "updated": "2026-07-21T15:45:22+00:00"
  },
  "IE00B4ND3602": {
    "symbol": "PPFB.SG",
    "companyName": "iShares Physical Gold ETC",
    "price": 69.315,
    "originalPrice": 69.315,
    "originalCurrency": "EUR",
    "change": 1.2849999999999966,
    "changesPercentage": 1.8888725562251896,
    "currency": "EUR",
    "updated": "2026-07-21T15:45:22+00:00"
  },
  "US90353T1007": {
    "symbol": "UBER",
    "companyName": "Uber Technologies",
    "price": 63.02480497852572,
    "originalPrice": 71.905,
    "originalCurrency": "USD",
    "change": -0.26500000000000057,
    "changesPercentage": -0.36718858251351055,
    "currency": "EUR",
    "updated": "2026-07-21T15:45:22+00:00"
  },
  "IE00B8HGT870": {
    "symbol": "3GOL.L",
    "companyName": "WisdomTree Gold 3x Daily Leveraged",
    "price": 113.40170041195547,
    "originalPrice": 129.38,
    "originalCurrency": "USD",
    "change": 6.009999999999991,
    "changesPercentage": 4.871524681851334,
    "currency": "EUR",
    "updated": "2026-07-21T15:45:22+00:00"
  },
  "DK0062498333": {
    "symbol": "NOV.DE",
    "companyName": "Novo Nordisk A/S",
    "price": 43.34,
    "originalPrice": 43.34,
    "originalCurrency": "EUR",
    "change": -0.634999999999998,
    "changesPercentage": -1.4440022740193246,
    "currency": "EUR",
    "updated": "2026-07-21T15:45:22+00:00"
  },
  "IE00B4NCWG09": {
    "symbol": "ISLN.L",
    "companyName": "iShares Physical Silver ETC",
    "price": 49.30756420369884,
    "originalPrice": 56.255,
    "originalCurrency": "USD",
    "change": 2.0575000000000045,
    "changesPercentage": 3.796300567369352,
    "currency": "EUR",
    "updated": "2026-07-21T15:45:22+00:00"
  },
  "NL0009434992": {
    "symbol": "LYB",
    "companyName": "LyondellBasell Industries",
    "price": 54.26417740380401,
    "originalPrice": 61.91,
    "originalCurrency": "USD",
    "change": 1.1799999999999997,
    "changesPercentage": 1.9430265107854432,
    "currency": "EUR",
    "updated": "2026-07-21T15:45:22+00:00"
  },
  "ES0157261019": {
    "symbol": "ROVI.MC",
    "companyName": "Laboratorios Rovi",
    "price": 54.65,
    "originalPrice": 54.65,
    "originalCurrency": "EUR",
    "change": 0.6000000000000014,
    "changesPercentage": 1.110083256244221,
    "currency": "EUR",
    "updated": "2026-07-21T15:45:22+00:00"
  },
  "KYG017191142": {
    "symbol": "2RR.F",
    "companyName": "Alibaba Group Holding",
    "price": 12.94,
    "originalPrice": 12.94,
    "originalCurrency": "EUR",
    "change": -0.3000000000000007,
    "changesPercentage": -2.2658610271903377,
    "currency": "EUR",
    "updated": "2026-07-21T15:45:22+00:00"
  }
}