{
  "IE00B5BMR087": {
    "symbol": "SXR8.DE",
    "companyName": "iShares Core S&P 500 UCITS ETF",
    "price": 708.66,
    "originalPrice": 708.66,
    "originalCurrency": "EUR",
    "change": 2.5399999999999636,
    "changesPercentage": 0.3597122302158222,
    "currency": "EUR",
    "updated": "2026-07-06T14:16:59+00:00"
  },
  "IE00B4ND3602": {
    "symbol": "PPFB.SG",
    "companyName": "iShares Physical Gold ETC",
    "price": 70.38,
    "originalPrice": 70.38,
    "originalCurrency": "EUR",
    "change": -0.29000000000000625,
    "changesPercentage": -0.41035800198104744,
    "currency": "EUR",
    "updated": "2026-07-06T14:16:59+00:00"
  },
  "US90353T1007": {
    "symbol": "UBER",
    "companyName": "Uber Technologies",
    "price": 63.571491112862276,
    "originalPrice": 72.605,
    "originalCurrency": "USD",
    "change": -1.8250000000000028,
    "changesPercentage": -2.451968292355237,
    "currency": "EUR",
    "updated": "2026-07-06T14:16:59+00:00"
  },
  "IE00B8HGT870": {
    "symbol": "3GOL.L",
    "companyName": "WisdomTree Gold 3x Daily Leveraged",
    "price": 120.17336485421592,
    "originalPrice": 137.25,
    "originalCurrency": "USD",
    "change": -2.7249999999999943,
    "changesPercentage": -1.9467762100375028,
    "currency": "EUR",
    "updated": "2026-07-06T14:16:59+00:00"
  },
  "DK0062498333": {
    "symbol": "NOV.DE",
    "companyName": "Novo Nordisk A/S",
    "price": 42.745,
    "originalPrice": 42.745,
    "originalCurrency": "EUR",
    "change": -0.855000000000004,
    "changesPercentage": -1.9610091743119358,
    "currency": "EUR",
    "updated": "2026-07-06T14:16:59+00:00"
  },
  "IE00B4NCWG09": {
    "symbol": "ISLN.L",
    "companyName": "iShares Physical Silver ETC",
    "price": 51.59618247088696,
    "originalPrice": 58.928,
    "originalCurrency": "USD",
    "change": -0.34200000000000585,
    "changesPercentage": -0.5770204150497821,
    "currency": "EUR",
    "updated": "2026-07-06T14:16:59+00:00"
  },
  "NL0009434992": {
    "symbol": "LYB",
    "companyName": "LyondellBasell Industries",
    "price": 45.96795376937221,
    "originalPrice": 52.5,
    "originalCurrency": "USD",
    "change": -0.8599999999999994,
    "changesPercentage": -1.6116941529235373,
    "currency": "EUR",
    "updated": "2026-07-06T14:16:59+00:00"
  },
  "ES0157261019": {
    "symbol": "ROVI.MC",
    "companyName": "Laboratorios Rovi",
    "price": 57.05,
    "originalPrice": 57.05,
    "originalCurrency": "EUR",
    "change": 0.14999999999999858,
    "changesPercentage": 0.26362038664323123,
    "currency": "EUR",
    "updated": "2026-07-06T14:16:59+00:00"
  },
  "KYG017191142": {
    "symbol": "2RR.F",
    "companyName": "Alibaba Group Holding",
    "price": 10.86,
    "originalPrice": 10.86,
    "originalCurrency": "EUR",
    "change": 0.35999999999999943,
    "changesPercentage": 3.428571428571423,
    "currency": "EUR",
    "updated": "2026-07-06T14:16:59+00:00"
  }
}